Metadata-Version: 1.0
Name: gaussandbinom-probability
Version: 0.2
Summary: Gaussian and Binomial distributions
Home-page: UNKNOWN
Author: Akif Acar
Author-email: mehmetakifacar@gmail.com
License: UNKNOWN
Platform: UNKNOWN
